docp_dbi/__init__.py
docp_dbi/_version.py
docp_dbi/changelog.py
docp_dbi/databases/_embeddingfunctions.py
docp_dbi/databases/chroma.py
docp_dbi-1.0.0.dist-info/licenses/LICENSE
docp_dbi-1.0.0.dist-info/METADATA
docp_dbi-1.0.0.dist-info/WHEEL
docp_dbi-1.0.0.dist-info/top_level.txt
docp_dbi-1.0.0.dist-info/RECORD
