Metadata-Version: 2.4
Name: docp-dbi
Version: 1.0.0
Summary: A basic document parsing utility. (Database Interface)
Author-email: The Developers <development@s3dev.uk>
License-Expression: GPL-3.0-or-later
Project-URL: Documentation, https://docp-dbi.readthedocs.io
Project-URL: Homepage, https://github.com/s3dev/docp-dbi
Project-URL: Repository, https://github.com/s3dev/docp-dbi
Keywords: database,document,embeddings,library,parsing,utility,utilities,vector database
Classifier: Development Status :: 5 - Production/Stable
Classifier: Intended Audience :: Developers
Classifier: Intended Audience :: End Users/Desktop
Classifier: Programming Language :: Python :: 3.11
Classifier: Programming Language :: Python :: 3.12
Classifier: Programming Language :: Python :: 3.13
Classifier: Programming Language :: Python :: 3.14
Classifier: Programming Language :: Python :: Implementation :: CPython
Classifier: Operating System :: POSIX :: Linux
Classifier: Operating System :: Microsoft :: Windows
Classifier: Topic :: Software Development
Classifier: Topic :: Software Development :: Libraries
Classifier: Topic :: Utilities
Requires-Python: >=3.11
License-File: LICENSE
Requires-Dist: ipywidgets>=8.1.8
Requires-Dist: langchain_chroma>=1.1.0
Requires-Dist: sentence_transformers>=3.4.0
Requires-Dist: torch>=2.9.0
Dynamic: license-file
